README.md
setup.py
Adafruit_AMG88xx/Adafruit_AMG88xx.py
Adafruit_AMG88xx/__init__.py
Adafruit_AMG88xx.egg-info/PKG-INFO
Adafruit_AMG88xx.egg-info/SOURCES.txt
Adafruit_AMG88xx.egg-info/dependency_links.txt
Adafruit_AMG88xx.egg-info/requires.txt
Adafruit_AMG88xx.egg-info/top_level.txt