Metadata-Version: 2.1
Name: Adafruit-AMG88xx
Version: 1.4.3
Summary: Python library to use the AMG88xx Grid-EYE 8x8 thermal sensor with raspberry pi or other linux boards.
Home-page: https://github.com/adafruit/Adafruit_AMG88xx_python/
Author: Dean Miller
Author-email: dean@adafruit.com
License: MIT
Platform: UNKNOWN
Classifier: Development Status :: 4 - Beta
Classifier: Operating System :: POSIX :: Linux
Classifier: License :: OSI Approved :: MIT License
Classifier: Intended Audience :: Developers
Classifier: Programming Language :: Python :: 2.7
Classifier: Programming Language :: Python :: 3
Classifier: Topic :: Software Development
Classifier: Topic :: System :: Hardware
